eol_check/__init__.py
eol_check/__main__.py
eol_check/cli.py
eol_check/core.py
eol_check/ui.py
eol_check-0.2.0.dist-info/licenses/LICENSE
eol_check-0.2.0.dist-info/METADATA
eol_check-0.2.0.dist-info/WHEEL
eol_check-0.2.0.dist-info/entry_points.txt
eol_check-0.2.0.dist-info/top_level.txt
eol_check-0.2.0.dist-info/RECORD
