Metadata-Version: 2.4
Name: eol-check
Version: 0.2.0
Summary: A tool to check the end-of-life status of software dependencies
Author-email: Lin Ye <31615967@qq.com>
License-Expression: MIT
Project-URL: Bug Tracker, https://github.com/yourlin/eol-check/issues
Project-URL: Documentation, https://github.com/yourlin/eol-check
Project-URL: Source Code, https://github.com/yourlin/eol-check
Keywords: dependency,eol,end-of-life,security,maintenance,java,python,nodejs
Classifier: Development Status :: 4 - Beta
Classifier: Intended Audience :: Developers
Classifier: Intended Audience :: System Administrators
Classifier: Programming Language :: Python :: 3
Classifier: Programming Language :: Python :: 3.8
Classifier: Programming Language :: Python :: 3.9
Classifier: Programming Language :: Python :: 3.10
Classifier: Programming Language :: Python :: 3.11
Classifier: Programming Language :: Python :: 3.12
Classifier: Operating System :: OS Independent
Classifier: Topic :: Software Development
Classifier: Topic :: Software Development :: Libraries :: Python Modules
Classifier: Topic :: System :: Software Distribution
Requires-Python: >=3.8
License-File: LICENSE
Requires-Dist: requests>=2.25.0
Requires-Dist: toml>=0.10.2
Requires-Dist: streamlit>=1.22.0
Requires-Dist: numpy<2.0.0
Dynamic: license-file
